sequoia/__init__.py
sequoia/client.py
sequoia/codecs.py
sequoia/exceptions.py
sequoia/request.py
sequoia/response.py
sequoia/types.py
sequoia_client_sdk_async-0.4.0.dist-info/LICENSE
sequoia_client_sdk_async-0.4.0.dist-info/WHEEL
sequoia_client_sdk_async-0.4.0.dist-info/METADATA
sequoia_client_sdk_async-0.4.0.dist-info/RECORD
