Metadata-Version: 2.1
Name: sequoia-client-sdk-async
Version: 0.4.0
Summary: 
Home-page: https://github.com/pikselpalette/sequoia-python-client-sdk-async
License: GPL-3.0+
Keywords: piksel,sequoia,client,sdk,asyncio
Author: José Antonio Perdiguero López
Author-email: perdy@perdy.io
Requires-Python: >=3.6,<4.0
Classifier: Development Status :: 5 - Production/Stable
Classifier: Intended Audience :: Developers
Classifier: License :: OSI Approved :: GNU General Public License v3 or later (GPLv3+)
Classifier: Programming Language :: Python :: 3
Classifier: Programming Language :: Python :: 3.6
Classifier: Programming Language :: Python :: 3.7
Classifier: Programming Language :: Python :: 3.8
Classifier: Topic :: Internet :: WWW/HTTP :: HTTP Servers
Classifier: Topic :: Software Development
Classifier: Topic :: Software Development :: Libraries
Requires-Dist: backoff (>=1.10.0,<2.0.0)
Requires-Dist: httpx (>=0.11.1,<0.12.0)
Requires-Dist: isodate (>=0.6.0,<0.7.0)
Project-URL: Repository, https://github.com/pikselpalette/sequoia-python-client-sdk-async
